peachrecorder/__init__.py
peachrecorder/__main__.py
peachrecorder/har_dump.py
peachrecorder/main.py
peachapisec_recorder-1.5.41.dist-info/METADATA
peachapisec_recorder-1.5.41.dist-info/WHEEL
peachapisec_recorder-1.5.41.dist-info/eager_resources.txt
peachapisec_recorder-1.5.41.dist-info/entry_points.txt
peachapisec_recorder-1.5.41.dist-info/top_level.txt
peachapisec_recorder-1.5.41.dist-info/RECORD
